gitlogstats/GitLogsParser.py
gitlogstats/__init__.py
gitlogstats/__main__.py
gitlogstats-1.0.4.dist-info/METADATA
gitlogstats-1.0.4.dist-info/WHEEL
gitlogstats-1.0.4.dist-info/entry_points.txt
gitlogstats-1.0.4.dist-info/licenses/LICENSE
gitlogstats-1.0.4.dist-info/RECORD
