Metadata-Version: 2.1
Name: gitlogstats
Version: 1.0.4
Summary: Track developers' contributions to one or more git repositories within a particular time range.
Project-URL: Homepage, https://github.com/bloombar/git-developer-contribution-analysis
Project-URL: Repository, https://github.com/bloombar/git-developer-contribution-analysis.git
Project-URL: Bug Tracker, https://github.com/bloombar/git-developer-contribution-analysis/issues
Author-email: Foo Barstein <foo.barstein@onepotcooking.com>
License:                     GNU GENERAL PUBLIC LICENSE
License-File: LICENSE
Keywords: analysis,contribution,developer,git,log,report
Classifier: Intended Audience :: Education
Classifier: License :: OSI Approved :: GNU General Public License v3 (GPLv3)
Classifier: Operating System :: OS Independent
Classifier: Programming Language :: Python :: 3
Requires-Python: >=3.7
Provides-Extra: dev
Requires-Dist: pytest; extra == 'dev'
